chessdotcom/__init__.py
chessdotcom/aio.py
chessdotcom/client.py
chessdotcom/types.py
chessdotcom/utils.py
nav_chess_com-2.2.0.dist-info/LICENSE
nav_chess_com-2.2.0.dist-info/METADATA
nav_chess_com-2.2.0.dist-info/WHEEL
nav_chess_com-2.2.0.dist-info/RECORD
