Metadata-Version: 2.1
Name: nav-chess-com
Version: 2.2.0
Summary: Python Wrapper for Chess.com API
License: MIT
Author: Artur Saradzhyan
Author-email: sarartur.ruk@gmail.com
Requires-Python: >=3.9,<4.0
Classifier: License :: OSI Approved :: MIT License
Classifier: Programming Language :: Python :: 3
Classifier: Programming Language :: Python :: 3.9
Classifier: Programming Language :: Python :: 3.10
Classifier: Programming Language :: Python :: 3.11
Classifier: Programming Language :: Python :: 3.12
Requires-Dist: aiohttp (>=3.9.5,<4.0.0)
Requires-Dist: requests (>=2.32.3,<3.0.0)
